{"trial_id": "0125", "hyperparameters": {"space": [{"class_name": "Int", "config": {"name": "units", "default": null, "conditions": [], "min_value": 16, "max_value": 64, "step": 16, "sampling": "linear"}}], "values": {"units": 32, "tuner/epochs": 7, "tuner/initial_epoch": 0, "tuner/bracket": 3, "tuner/round": 0}}, "metrics": {"metrics": {"loss": {"direction": "min", "observations": [{"value": [0.10205569118261337], "step": 6}]}, "accuracy": {"direction": "max", "observations": [{"value": [0.9652326107025146], "step": 6}]}, "val_loss": {"direction": "min", "observations": [{"value": [0.09499532729387283], "step": 6}]}, "val_accuracy": {"direction": "max", "observations": [{"value": [0.9729999899864197], "step": 6}]}}}, "score": 0.9652326107025146, "best_step": 6, "status": "COMPLETED", "message": null}