{"trial_id": "0052", "hyperparameters": {"space": [{"class_name": "Int", "config": {"name": "units", "default": null, "conditions": [], "min_value": 4, "max_value": 64, "step": 5, "sampling": "linear"}}], "values": {"units": 14, "tuner/epochs": 2, "tuner/initial_epoch": 0, "tuner/bracket": 4, "tuner/round": 0}}, "metrics": {"metrics": {"loss": {"direction": "min", "observations": [{"value": [0.004561997018754482], "step": 1}]}, "mse": {"direction": "min", "observations": [{"value": [0.004561997018754482], "step": 1}]}, "val_loss": {"direction": "min", "observations": [{"value": [0.004562597721815109], "step": 1}]}, "val_mse": {"direction": "min", "observations": [{"value": [0.004562597721815109], "step": 1}]}}}, "score": 0.004561997018754482, "best_step": 1, "status": "COMPLETED", "message": null}